deutschspiel/__init__.py
deutschspiel/verbs.py
deutschspiel-0.1.0.dist-info/WHEEL
deutschspiel-0.1.0.dist-info/METADATA
deutschspiel-0.1.0.dist-info/RECORD
