Metadata-Version: 2.1
Name: deutschspiel
Version: 0.1.0
Summary: Framework to handle German Grammar
Author: Marco Menezes
Author-email: marcoaurelioreislima@gmail.com
Requires-Python: >=3.6,<4.0
Classifier: Programming Language :: Python :: 3
Classifier: Programming Language :: Python :: 3.6
Classifier: Programming Language :: Python :: 3.7
Classifier: Programming Language :: Python :: 3.8
Classifier: Programming Language :: Python :: 3.9
Requires-Dist: pandas (>=0.25,<1.0)
